pyudev/__init__.py
pyudev/_compat.py
pyudev/_errors.py
pyudev/_qt_base.py
pyudev/_util.py
pyudev/core.py
pyudev/discover.py
pyudev/glib.py
pyudev/monitor.py
pyudev/pyqt4.py
pyudev/pyqt5.py
pyudev/pyside.py
pyudev/version.py
pyudev/wx.py
pyudev/_ctypeslib/__init__.py
pyudev/_ctypeslib/_errorcheckers.py
pyudev/_ctypeslib/libc.py
pyudev/_ctypeslib/libudev.py
pyudev/_ctypeslib/utils.py
pyudev/_os/__init__.py
pyudev/_os/pipe.py
pyudev/_os/poll.py
pyudev/device/__init__.py
pyudev/device/_device.py
pyudev-0.23.2.dist-info/COPYING
pyudev-0.23.2.dist-info/METADATA
pyudev-0.23.2.dist-info/WHEEL
pyudev-0.23.2.dist-info/top_level.txt
pyudev-0.23.2.dist-info/RECORD
