Metadata-Version: 2.1
Name: pyudev
Version: 0.23.2
Summary: A libudev binding
Home-page: http://pyudev.readthedocs.org/
Author: Sebastian Wiesner
Author-email: lunaryorn@gmail.com
License: LGPL 2.1+
Platform: Linux
Classifier: Development Status :: 5 - Production/Stable
Classifier: Intended Audience :: Developers
Classifier: License :: OSI Approved :: GNU Library or Lesser General Public License (LGPL)
Classifier: Operating System :: POSIX :: Linux
Classifier: Programming Language :: Python
Classifier: Programming Language :: Python :: 3
Classifier: Programming Language :: Python :: Implementation :: CPython
Classifier: Programming Language :: Python :: Implementation :: PyPy
Classifier: Topic :: Software Development :: Libraries
Classifier: Topic :: System :: Hardware
Classifier: Topic :: System :: Operating System Kernels :: Linux
License-File: COPYING
